[
  {
    "region":"전국",
    "year":2000,
    "item":"registered_households",
    "value":15765275.0
  },
  {
    "region":"전국",
    "year":2001,
    "item":"registered_households",
    "value":16080992.0
  },
  {
    "region":"전국",
    "year":2002,
    "item":"registered_households",
    "value":16489107.0
  },
  {
    "region":"전국",
    "year":2003,
    "item":"registered_households",
    "value":16987634.0
  },
  {
    "region":"전국",
    "year":2004,
    "item":"registered_households",
    "value":17391932.0
  },
  {
    "region":"전국",
    "year":2005,
    "item":"registered_households",
    "value":17857511.0
  },
  {
    "region":"전국",
    "year":2006,
    "item":"registered_households",
    "value":18326619.0
  },
  {
    "region":"전국",
    "year":2007,
    "item":"registered_households",
    "value":18687694.0
  },
  {
    "region":"전국",
    "year":2008,
    "item":"registered_households",
    "value":19005339.0
  },
  {
    "region":"전국",
    "year":2009,
    "item":"registered_households",
    "value":19261292.0
  },
  {
    "region":"전국",
    "year":2010,
    "item":"registered_households",
    "value":19865179.0
  },
  {
    "region":"전국",
    "year":2011,
    "item":"registered_households",
    "value":20033142.0
  },
  {
    "region":"전국",
    "year":2012,
    "item":"registered_households",
    "value":20211770.0
  },
  {
    "region":"전국",
    "year":2013,
    "item":"registered_households",
    "value":20456588.0
  },
  {
    "region":"전국",
    "year":2014,
    "item":"registered_households",
    "value":20724094.0
  },
  {
    "region":"전국",
    "year":2015,
    "item":"registered_households",
    "value":21011152.0
  },
  {
    "region":"전국",
    "year":2016,
    "item":"registered_households",
    "value":21294009.0
  },
  {
    "region":"전국",
    "year":2017,
    "item":"registered_households",
    "value":21632851.0
  },
  {
    "region":"전국",
    "year":2018,
    "item":"registered_households",
    "value":22042947.0
  },
  {
    "region":"전국",
    "year":2019,
    "item":"registered_households",
    "value":22481466.0
  },
  {
    "region":"전국",
    "year":2020,
    "item":"registered_households",
    "value":23093108.0
  },
  {
    "region":"전국",
    "year":2021,
    "item":"registered_households",
    "value":23472895.0
  },
  {
    "region":"전국",
    "year":2022,
    "item":"registered_households",
    "value":23705814.0
  },
  {
    "region":"전국",
    "year":2023,
    "item":"registered_households",
    "value":23914851.0
  },
  {
    "region":"전국",
    "year":2024,
    "item":"registered_households",
    "value":24118928.0
  },
  {
    "region":"서울특별시",
    "year":2000,
    "item":"registered_households",
    "value":3540492.0
  },
  {
    "region":"서울특별시",
    "year":2001,
    "item":"registered_households",
    "value":3570228.0
  },
  {
    "region":"서울특별시",
    "year":2002,
    "item":"registered_households",
    "value":3623929.0
  },
  {
    "region":"서울특별시",
    "year":2003,
    "item":"registered_households",
    "value":3714697.0
  },
  {
    "region":"서울특별시",
    "year":2004,
    "item":"registered_households",
    "value":3780305.0
  },
  {
    "region":"서울특별시",
    "year":2005,
    "item":"registered_households",
    "value":3871024.0
  },
  {
    "region":"서울특별시",
    "year":2006,
    "item":"registered_households",
    "value":3978938.0
  },
  {
    "region":"서울특별시",
    "year":2007,
    "item":"registered_households",
    "value":4046086.0
  },
  {
    "region":"서울특별시",
    "year":2008,
    "item":"registered_households",
    "value":4097562.0
  },
  {
    "region":"서울특별시",
    "year":2009,
    "item":"registered_households",
    "value":4116660.0
  },
  {
    "region":"서울특별시",
    "year":2010,
    "item":"registered_households",
    "value":4224181.0
  },
  {
    "region":"서울특별시",
    "year":2011,
    "item":"registered_households",
    "value":4192752.0
  },
  {
    "region":"서울특별시",
    "year":2012,
    "item":"registered_households",
    "value":4177970.0
  },
  {
    "region":"서울특별시",
    "year":2013,
    "item":"registered_households",
    "value":4182351.0
  },
  {
    "region":"서울특별시",
    "year":2014,
    "item":"registered_households",
    "value":4194176.0
  },
  {
    "region":"서울특별시",
    "year":2015,
    "item":"registered_households",
    "value":4189948.0
  },
  {
    "region":"서울특별시",
    "year":2016,
    "item":"registered_households",
    "value":4189839.0
  },
  {
    "region":"서울특별시",
    "year":2017,
    "item":"registered_households",
    "value":4220082.0
  },
  {
    "region":"서울특별시",
    "year":2018,
    "item":"registered_households",
    "value":4263868.0
  },
  {
    "region":"서울특별시",
    "year":2019,
    "item":"registered_households",
    "value":4327605.0
  },
  {
    "region":"서울특별시",
    "year":2020,
    "item":"registered_households",
    "value":4417954.0
  },
  {
    "region":"서울특별시",
    "year":2021,
    "item":"registered_households",
    "value":4426007.0
  },
  {
    "region":"서울특별시",
    "year":2022,
    "item":"registered_households",
    "value":4446296.0
  },
  {
    "region":"서울특별시",
    "year":2023,
    "item":"registered_households",
    "value":4469417.0
  },
  {
    "region":"서울특별시",
    "year":2024,
    "item":"registered_households",
    "value":4482063.0
  },
  {
    "region":"부산광역시",
    "year":2000,
    "item":"registered_households",
    "value":1199804.0
  },
  {
    "region":"부산광역시",
    "year":2001,
    "item":"registered_households",
    "value":1210902.0
  },
  {
    "region":"부산광역시",
    "year":2002,
    "item":"registered_households",
    "value":1219902.0
  },
  {
    "region":"부산광역시",
    "year":2003,
    "item":"registered_households",
    "value":1236262.0
  },
  {
    "region":"부산광역시",
    "year":2004,
    "item":"registered_households",
    "value":1251069.0
  },
  {
    "region":"부산광역시",
    "year":2005,
    "item":"registered_households",
    "value":1270612.0
  },
  {
    "region":"부산광역시",
    "year":2006,
    "item":"registered_households",
    "value":1288671.0
  },
  {
    "region":"부산광역시",
    "year":2007,
    "item":"registered_households",
    "value":1300692.0
  },
  {
    "region":"부산광역시",
    "year":2008,
    "item":"registered_households",
    "value":1311724.0
  },
  {
    "region":"부산광역시",
    "year":2009,
    "item":"registered_households",
    "value":1323771.0
  },
  {
    "region":"부산광역시",
    "year":2010,
    "item":"registered_households",
    "value":1371346.0
  },
  {
    "region":"부산광역시",
    "year":2011,
    "item":"registered_households",
    "value":1381257.0
  },
  {
    "region":"부산광역시",
    "year":2012,
    "item":"registered_households",
    "value":1389526.0
  },
  {
    "region":"부산광역시",
    "year":2013,
    "item":"registered_households",
    "value":1404663.0
  },
  {
    "region":"부산광역시",
    "year":2014,
    "item":"registered_households",
    "value":1421648.0
  },
  {
    "region":"부산광역시",
    "year":2015,
    "item":"registered_households",
    "value":1437818.0
  },
  {
    "region":"부산광역시",
    "year":2016,
    "item":"registered_households",
    "value":1451270.0
  },
  {
    "region":"부산광역시",
    "year":2017,
    "item":"registered_households",
    "value":1467555.0
  },
  {
    "region":"부산광역시",
    "year":2018,
    "item":"registered_households",
    "value":1480468.0
  },
  {
    "region":"부산광역시",
    "year":2019,
    "item":"registered_households",
    "value":1497908.0
  },
  {
    "region":"부산광역시",
    "year":2020,
    "item":"registered_households",
    "value":1530431.0
  },
  {
    "region":"부산광역시",
    "year":2021,
    "item":"registered_households",
    "value":1544663.0
  },
  {
    "region":"부산광역시",
    "year":2022,
    "item":"registered_households",
    "value":1555867.0
  },
  {
    "region":"부산광역시",
    "year":2023,
    "item":"registered_households",
    "value":1564588.0
  },
  {
    "region":"부산광역시",
    "year":2024,
    "item":"registered_households",
    "value":1570403.0
  },
  {
    "region":"대구광역시",
    "year":2000,
    "item":"registered_households",
    "value":805779.0
  },
  {
    "region":"대구광역시",
    "year":2001,
    "item":"registered_households",
    "value":815709.0
  },
  {
    "region":"대구광역시",
    "year":2002,
    "item":"registered_households",
    "value":827177.0
  },
  {
    "region":"대구광역시",
    "year":2003,
    "item":"registered_households",
    "value":845242.0
  },
  {
    "region":"대구광역시",
    "year":2004,
    "item":"registered_households",
    "value":853142.0
  },
  {
    "region":"대구광역시",
    "year":2005,
    "item":"registered_households",
    "value":865766.0
  },
  {
    "region":"대구광역시",
    "year":2006,
    "item":"registered_households",
    "value":875173.0
  },
  {
    "region":"대구광역시",
    "year":2007,
    "item":"registered_households",
    "value":883920.0
  },
  {
    "region":"대구광역시",
    "year":2008,
    "item":"registered_households",
    "value":894969.0
  },
  {
    "region":"대구광역시",
    "year":2009,
    "item":"registered_households",
    "value":906470.0
  },
  {
    "region":"대구광역시",
    "year":2010,
    "item":"registered_households",
    "value":934598.0
  },
  {
    "region":"대구광역시",
    "year":2011,
    "item":"registered_households",
    "value":940770.0
  },
  {
    "region":"대구광역시",
    "year":2012,
    "item":"registered_households",
    "value":948652.0
  },
  {
    "region":"대구광역시",
    "year":2013,
    "item":"registered_households",
    "value":960265.0
  },
  {
    "region":"대구광역시",
    "year":2014,
    "item":"registered_households",
    "value":970618.0
  },
  {
    "region":"대구광역시",
    "year":2015,
    "item":"registered_households",
    "value":982360.0
  },
  {
    "region":"대구광역시",
    "year":2016,
    "item":"registered_households",
    "value":994220.0
  },
  {
    "region":"대구광역시",
    "year":2017,
    "item":"registered_households",
    "value":1006753.0
  },
  {
    "region":"대구광역시",
    "year":2018,
    "item":"registered_households",
    "value":1021266.0
  },
  {
    "region":"대구광역시",
    "year":2019,
    "item":"registered_households",
    "value":1031251.0
  },
  {
    "region":"대구광역시",
    "year":2020,
    "item":"registered_households",
    "value":1056627.0
  },
  {
    "region":"대구광역시",
    "year":2021,
    "item":"registered_households",
    "value":1063893.0
  },
  {
    "region":"대구광역시",
    "year":2022,
    "item":"registered_households",
    "value":1070873.0
  },
  {
    "region":"대구광역시",
    "year":2023,
    "item":"registered_households",
    "value":1094148.0
  },
  {
    "region":"대구광역시",
    "year":2024,
    "item":"registered_households",
    "value":1104130.0
  },
  {
    "region":"인천광역시",
    "year":2000,
    "item":"registered_households",
    "value":829164.0
  },
  {
    "region":"인천광역시",
    "year":2001,
    "item":"registered_households",
    "value":845739.0
  },
  {
    "region":"인천광역시",
    "year":2002,
    "item":"registered_households",
    "value":872057.0
  },
  {
    "region":"인천광역시",
    "year":2003,
    "item":"registered_households",
    "value":891606.0
  },
  {
    "region":"인천광역시",
    "year":2004,
    "item":"registered_households",
    "value":908673.0
  },
  {
    "region":"인천광역시",
    "year":2005,
    "item":"registered_households",
    "value":933686.0
  },
  {
    "region":"인천광역시",
    "year":2006,
    "item":"registered_households",
    "value":965302.0
  },
  {
    "region":"인천광역시",
    "year":2007,
    "item":"registered_households",
    "value":995712.0
  },
  {
    "region":"인천광역시",
    "year":2008,
    "item":"registered_households",
    "value":1014755.0
  },
  {
    "region":"인천광역시",
    "year":2009,
    "item":"registered_households",
    "value":1026936.0
  },
  {
    "region":"인천광역시",
    "year":2010,
    "item":"registered_households",
    "value":1059664.0
  },
  {
    "region":"인천광역시",
    "year":2011,
    "item":"registered_households",
    "value":1077563.0
  },
  {
    "region":"인천광역시",
    "year":2012,
    "item":"registered_households",
    "value":1097491.0
  },
  {
    "region":"인천광역시",
    "year":2013,
    "item":"registered_households",
    "value":1118988.0
  },
  {
    "region":"인천광역시",
    "year":2014,
    "item":"registered_households",
    "value":1136280.0
  },
  {
    "region":"인천광역시",
    "year":2015,
    "item":"registered_households",
    "value":1154004.0
  },
  {
    "region":"인천광역시",
    "year":2016,
    "item":"registered_households",
    "value":1171399.0
  },
  {
    "region":"인천광역시",
    "year":2017,
    "item":"registered_households",
    "value":1188917.0
  },
  {
    "region":"인천광역시",
    "year":2018,
    "item":"registered_households",
    "value":1213201.0
  },
  {
    "region":"인천광역시",
    "year":2019,
    "item":"registered_households",
    "value":1238641.0
  },
  {
    "region":"인천광역시",
    "year":2020,
    "item":"registered_households",
    "value":1267956.0
  },
  {
    "region":"인천광역시",
    "year":2021,
    "item":"registered_households",
    "value":1298647.0
  },
  {
    "region":"인천광역시",
    "year":2022,
    "item":"registered_households",
    "value":1322632.0
  },
  {
    "region":"인천광역시",
    "year":2023,
    "item":"registered_households",
    "value":1350912.0
  },
  {
    "region":"인천광역시",
    "year":2024,
    "item":"registered_households",
    "value":1373827.0
  },
  {
    "region":"광주광역시",
    "year":2000,
    "item":"registered_households",
    "value":430376.0
  },
  {
    "region":"광주광역시",
    "year":2001,
    "item":"registered_households",
    "value":439620.0
  },
  {
    "region":"광주광역시",
    "year":2002,
    "item":"registered_households",
    "value":449469.0
  },
  {
    "region":"광주광역시",
    "year":2003,
    "item":"registered_households",
    "value":460647.0
  },
  {
    "region":"광주광역시",
    "year":2004,
    "item":"registered_households",
    "value":469847.0
  },
  {
    "region":"광주광역시",
    "year":2005,
    "item":"registered_households",
    "value":481935.0
  },
  {
    "region":"광주광역시",
    "year":2006,
    "item":"registered_households",
    "value":495065.0
  },
  {
    "region":"광주광역시",
    "year":2007,
    "item":"registered_households",
    "value":503844.0
  },
  {
    "region":"광주광역시",
    "year":2008,
    "item":"registered_households",
    "value":513021.0
  },
  {
    "region":"광주광역시",
    "year":2009,
    "item":"registered_households",
    "value":524093.0
  },
  {
    "region":"광주광역시",
    "year":2010,
    "item":"registered_households",
    "value":540875.0
  },
  {
    "region":"광주광역시",
    "year":2011,
    "item":"registered_households",
    "value":549105.0
  },
  {
    "region":"광주광역시",
    "year":2012,
    "item":"registered_households",
    "value":555538.0
  },
  {
    "region":"광주광역시",
    "year":2013,
    "item":"registered_households",
    "value":563599.0
  },
  {
    "region":"광주광역시",
    "year":2014,
    "item":"registered_households",
    "value":573043.0
  },
  {
    "region":"광주광역시",
    "year":2015,
    "item":"registered_households",
    "value":580427.0
  },
  {
    "region":"광주광역시",
    "year":2016,
    "item":"registered_households",
    "value":586464.0
  },
  {
    "region":"광주광역시",
    "year":2017,
    "item":"registered_households",
    "value":592818.0
  },
  {
    "region":"광주광역시",
    "year":2018,
    "item":"registered_households",
    "value":603107.0
  },
  {
    "region":"광주광역시",
    "year":2019,
    "item":"registered_households",
    "value":616485.0
  },
  {
    "region":"광주광역시",
    "year":2020,
    "item":"registered_households",
    "value":633582.0
  },
  {
    "region":"광주광역시",
    "year":2021,
    "item":"registered_households",
    "value":645712.0
  },
  {
    "region":"광주광역시",
    "year":2022,
    "item":"registered_households",
    "value":652355.0
  },
  {
    "region":"광주광역시",
    "year":2023,
    "item":"registered_households",
    "value":655433.0
  },
  {
    "region":"광주광역시",
    "year":2024,
    "item":"registered_households",
    "value":658075.0
  },
  {
    "region":"대전광역시",
    "year":2000,
    "item":"registered_households",
    "value":439312.0
  },
  {
    "region":"대전광역시",
    "year":2001,
    "item":"registered_households",
    "value":450489.0
  },
  {
    "region":"대전광역시",
    "year":2002,
    "item":"registered_households",
    "value":463270.0
  },
  {
    "region":"대전광역시",
    "year":2003,
    "item":"registered_households",
    "value":479916.0
  },
  {
    "region":"대전광역시",
    "year":2004,
    "item":"registered_households",
    "value":492068.0
  },
  {
    "region":"대전광역시",
    "year":2005,
    "item":"registered_households",
    "value":505650.0
  },
  {
    "region":"대전광역시",
    "year":2006,
    "item":"registered_households",
    "value":518039.0
  },
  {
    "region":"대전광역시",
    "year":2007,
    "item":"registered_households",
    "value":525880.0
  },
  {
    "region":"대전광역시",
    "year":2008,
    "item":"registered_households",
    "value":531682.0
  },
  {
    "region":"대전광역시",
    "year":2009,
    "item":"registered_households",
    "value":538100.0
  },
  {
    "region":"대전광역시",
    "year":2010,
    "item":"registered_households",
    "value":555768.0
  },
  {
    "region":"대전광역시",
    "year":2011,
    "item":"registered_households",
    "value":566324.0
  },
  {
    "region":"대전광역시",
    "year":2012,
    "item":"registered_households",
    "value":575600.0
  },
  {
    "region":"대전광역시",
    "year":2013,
    "item":"registered_households",
    "value":584877.0
  },
  {
    "region":"대전광역시",
    "year":2014,
    "item":"registered_households",
    "value":592508.0
  },
  {
    "region":"대전광역시",
    "year":2015,
    "item":"registered_households",
    "value":597008.0
  },
  {
    "region":"대전광역시",
    "year":2016,
    "item":"registered_households",
    "value":606137.0
  },
  {
    "region":"대전광역시",
    "year":2017,
    "item":"registered_households",
    "value":614639.0
  },
  {
    "region":"대전광역시",
    "year":2018,
    "item":"registered_households",
    "value":624965.0
  },
  {
    "region":"대전광역시",
    "year":2019,
    "item":"registered_households",
    "value":635343.0
  },
  {
    "region":"대전광역시",
    "year":2020,
    "item":"registered_households",
    "value":652783.0
  },
  {
    "region":"대전광역시",
    "year":2021,
    "item":"registered_households",
    "value":664417.0
  },
  {
    "region":"대전광역시",
    "year":2022,
    "item":"registered_households",
    "value":673429.0
  },
  {
    "region":"대전광역시",
    "year":2023,
    "item":"registered_households",
    "value":680261.0
  },
  {
    "region":"대전광역시",
    "year":2024,
    "item":"registered_households",
    "value":687757.0
  },
  {
    "region":"울산광역시",
    "year":2000,
    "item":"registered_households",
    "value":322838.0
  },
  {
    "region":"울산광역시",
    "year":2001,
    "item":"registered_households",
    "value":331502.0
  },
  {
    "region":"울산광역시",
    "year":2002,
    "item":"registered_households",
    "value":338845.0
  },
  {
    "region":"울산광역시",
    "year":2003,
    "item":"registered_households",
    "value":348058.0
  },
  {
    "region":"울산광역시",
    "year":2004,
    "item":"registered_households",
    "value":356143.0
  },
  {
    "region":"울산광역시",
    "year":2005,
    "item":"registered_households",
    "value":365197.0
  },
  {
    "region":"울산광역시",
    "year":2006,
    "item":"registered_households",
    "value":373114.0
  },
  {
    "region":"울산광역시",
    "year":2007,
    "item":"registered_households",
    "value":380865.0
  },
  {
    "region":"울산광역시",
    "year":2008,
    "item":"registered_households",
    "value":389735.0
  },
  {
    "region":"울산광역시",
    "year":2009,
    "item":"registered_households",
    "value":394364.0
  },
  {
    "region":"울산광역시",
    "year":2010,
    "item":"registered_households",
    "value":405501.0
  },
  {
    "region":"울산광역시",
    "year":2011,
    "item":"registered_households",
    "value":412561.0
  },
  {
    "region":"울산광역시",
    "year":2012,
    "item":"registered_households",
    "value":422177.0
  },
  {
    "region":"울산광역시",
    "year":2013,
    "item":"registered_households",
    "value":431595.0
  },
  {
    "region":"울산광역시",
    "year":2014,
    "item":"registered_households",
    "value":442250.0
  },
  {
    "region":"울산광역시",
    "year":2015,
    "item":"registered_households",
    "value":451688.0
  },
  {
    "region":"울산광역시",
    "year":2016,
    "item":"registered_households",
    "value":455352.0
  },
  {
    "region":"울산광역시",
    "year":2017,
    "item":"registered_households",
    "value":458547.0
  },
  {
    "region":"울산광역시",
    "year":2018,
    "item":"registered_households",
    "value":461756.0
  },
  {
    "region":"울산광역시",
    "year":2019,
    "item":"registered_households",
    "value":468659.0
  },
  {
    "region":"울산광역시",
    "year":2020,
    "item":"registered_households",
    "value":476893.0
  },
  {
    "region":"울산광역시",
    "year":2021,
    "item":"registered_households",
    "value":482650.0
  },
  {
    "region":"울산광역시",
    "year":2022,
    "item":"registered_households",
    "value":486143.0
  },
  {
    "region":"울산광역시",
    "year":2023,
    "item":"registered_households",
    "value":490690.0
  },
  {
    "region":"울산광역시",
    "year":2024,
    "item":"registered_households",
    "value":495378.0
  },
  {
    "region":"세종특별자치시",
    "year":2000,
    "item":"registered_households",
    "value":null
  },
  {
    "region":"세종특별자치시",
    "year":2001,
    "item":"registered_households",
    "value":null
  },
  {
    "region":"세종특별자치시",
    "year":2002,
    "item":"registered_households",
    "value":null
  },
  {
    "region":"세종특별자치시",
    "year":2003,
    "item":"registered_households",
    "value":null
  },
  {
    "region":"세종특별자치시",
    "year":2004,
    "item":"registered_households",
    "value":null
  },
  {
    "region":"세종특별자치시",
    "year":2005,
    "item":"registered_households",
    "value":null
  },
  {
    "region":"세종특별자치시",
    "year":2006,
    "item":"registered_households",
    "value":null
  },
  {
    "region":"세종특별자치시",
    "year":2007,
    "item":"registered_households",
    "value":null
  },
  {
    "region":"세종특별자치시",
    "year":2008,
    "item":"registered_households",
    "value":null
  },
  {
    "region":"세종특별자치시",
    "year":2009,
    "item":"registered_households",
    "value":null
  },
  {
    "region":"세종특별자치시",
    "year":2010,
    "item":"registered_households",
    "value":null
  },
  {
    "region":"세종특별자치시",
    "year":2011,
    "item":"registered_households",
    "value":null
  },
  {
    "region":"세종특별자치시",
    "year":2012,
    "item":"registered_households",
    "value":46592.0
  },
  {
    "region":"세종특별자치시",
    "year":2013,
    "item":"registered_households",
    "value":50045.0
  },
  {
    "region":"세종특별자치시",
    "year":2014,
    "item":"registered_households",
    "value":62807.0
  },
  {
    "region":"세종특별자치시",
    "year":2015,
    "item":"registered_households",
    "value":81806.0
  },
  {
    "region":"세종특별자치시",
    "year":2016,
    "item":"registered_households",
    "value":94343.0
  },
  {
    "region":"세종특별자치시",
    "year":2017,
    "item":"registered_households",
    "value":109490.0
  },
  {
    "region":"세종특별자치시",
    "year":2018,
    "item":"registered_households",
    "value":123762.0
  },
  {
    "region":"세종특별자치시",
    "year":2019,
    "item":"registered_households",
    "value":135408.0
  },
  {
    "region":"세종특별자치시",
    "year":2020,
    "item":"registered_households",
    "value":144275.0
  },
  {
    "region":"세종특별자치시",
    "year":2021,
    "item":"registered_households",
    "value":153649.0
  },
  {
    "region":"세종특별자치시",
    "year":2022,
    "item":"registered_households",
    "value":159386.0
  },
  {
    "region":"세종특별자치시",
    "year":2023,
    "item":"registered_households",
    "value":160835.0
  },
  {
    "region":"세종특별자치시",
    "year":2024,
    "item":"registered_households",
    "value":163432.0
  },
  {
    "region":"경기도",
    "year":2000,
    "item":"registered_households",
    "value":3052102.0
  },
  {
    "region":"경기도",
    "year":2001,
    "item":"registered_households",
    "value":3191089.0
  },
  {
    "region":"경기도",
    "year":2002,
    "item":"registered_households",
    "value":3394937.0
  },
  {
    "region":"경기도",
    "year":2003,
    "item":"registered_households",
    "value":3592144.0
  },
  {
    "region":"경기도",
    "year":2004,
    "item":"registered_households",
    "value":3748325.0
  },
  {
    "region":"경기도",
    "year":2005,
    "item":"registered_households",
    "value":3910886.0
  },
  {
    "region":"경기도",
    "year":2006,
    "item":"registered_households",
    "value":4068786.0
  },
  {
    "region":"경기도",
    "year":2007,
    "item":"registered_households",
    "value":4183926.0
  },
  {
    "region":"경기도",
    "year":2008,
    "item":"registered_households",
    "value":4284475.0
  },
  {
    "region":"경기도",
    "year":2009,
    "item":"registered_households",
    "value":4359467.0
  },
  {
    "region":"경기도",
    "year":2010,
    "item":"registered_households",
    "value":4527282.0
  },
  {
    "region":"경기도",
    "year":2011,
    "item":"registered_households",
    "value":4579405.0
  },
  {
    "region":"경기도",
    "year":2012,
    "item":"registered_households",
    "value":4639665.0
  },
  {
    "region":"경기도",
    "year":2013,
    "item":"registered_households",
    "value":4712324.0
  },
  {
    "region":"경기도",
    "year":2014,
    "item":"registered_households",
    "value":4786718.0
  },
  {
    "region":"경기도",
    "year":2015,
    "item":"registered_households",
    "value":4885012.0
  },
  {
    "region":"경기도",
    "year":2016,
    "item":"registered_households",
    "value":5003406.0
  },
  {
    "region":"경기도",
    "year":2017,
    "item":"registered_households",
    "value":5131379.0
  },
  {
    "region":"경기도",
    "year":2018,
    "item":"registered_households",
    "value":5306214.0
  },
  {
    "region":"경기도",
    "year":2019,
    "item":"registered_households",
    "value":5468920.0
  },
  {
    "region":"경기도",
    "year":2020,
    "item":"registered_households",
    "value":5676401.0
  },
  {
    "region":"경기도",
    "year":2021,
    "item":"registered_households",
    "value":5841995.0
  },
  {
    "region":"경기도",
    "year":2022,
    "item":"registered_households",
    "value":5913694.0
  },
  {
    "region":"경기도",
    "year":2023,
    "item":"registered_households",
    "value":5978724.0
  },
  {
    "region":"경기도",
    "year":2024,
    "item":"registered_households",
    "value":6058202.0
  },
  {
    "region":"강원특별자치도",
    "year":2000,
    "item":"registered_households",
    "value":521728.0
  },
  {
    "region":"강원특별자치도",
    "year":2001,
    "item":"registered_households",
    "value":531123.0
  },
  {
    "region":"강원특별자치도",
    "year":2002,
    "item":"registered_households",
    "value":538613.0
  },
  {
    "region":"강원특별자치도",
    "year":2003,
    "item":"registered_households",
    "value":552319.0
  },
  {
    "region":"강원특별자치도",
    "year":2004,
    "item":"registered_households",
    "value":563355.0
  },
  {
    "region":"강원특별자치도",
    "year":2005,
    "item":"registered_households",
    "value":574019.0
  },
  {
    "region":"강원특별자치도",
    "year":2006,
    "item":"registered_households",
    "value":583890.0
  },
  {
    "region":"강원특별자치도",
    "year":2007,
    "item":"registered_households",
    "value":594360.0
  },
  {
    "region":"강원특별자치도",
    "year":2008,
    "item":"registered_households",
    "value":606950.0
  },
  {
    "region":"강원특별자치도",
    "year":2009,
    "item":"registered_households",
    "value":617693.0
  },
  {
    "region":"강원특별자치도",
    "year":2010,
    "item":"registered_households",
    "value":639001.0
  },
  {
    "region":"강원특별자치도",
    "year":2011,
    "item":"registered_households",
    "value":648649.0
  },
  {
    "region":"강원특별자치도",
    "year":2012,
    "item":"registered_households",
    "value":655301.0
  },
  {
    "region":"강원특별자치도",
    "year":2013,
    "item":"registered_households",
    "value":664913.0
  },
  {
    "region":"강원특별자치도",
    "year":2014,
    "item":"registered_households",
    "value":673978.0
  },
  {
    "region":"강원특별자치도",
    "year":2015,
    "item":"registered_households",
    "value":685005.0
  },
  {
    "region":"강원특별자치도",
    "year":2016,
    "item":"registered_households",
    "value":692254.0
  },
  {
    "region":"강원특별자치도",
    "year":2017,
    "item":"registered_households",
    "value":700265.0
  },
  {
    "region":"강원특별자치도",
    "year":2018,
    "item":"registered_households",
    "value":707245.0
  },
  {
    "region":"강원특별자치도",
    "year":2019,
    "item":"registered_households",
    "value":719524.0
  },
  {
    "region":"강원특별자치도",
    "year":2020,
    "item":"registered_households",
    "value":736301.0
  },
  {
    "region":"강원특별자치도",
    "year":2021,
    "item":"registered_households",
    "value":746220.0
  },
  {
    "region":"강원특별자치도",
    "year":2022,
    "item":"registered_households",
    "value":755481.0
  },
  {
    "region":"강원특별자치도",
    "year":2023,
    "item":"registered_households",
    "value":760635.0
  },
  {
    "region":"강원특별자치도",
    "year":2024,
    "item":"registered_households",
    "value":764834.0
  },
  {
    "region":"충청북도",
    "year":2000,
    "item":"registered_households",
    "value":491781.0
  },
  {
    "region":"충청북도",
    "year":2001,
    "item":"registered_households",
    "value":499739.0
  },
  {
    "region":"충청북도",
    "year":2002,
    "item":"registered_households",
    "value":508561.0
  },
  {
    "region":"충청북도",
    "year":2003,
    "item":"registered_households",
    "value":522501.0
  },
  {
    "region":"충청북도",
    "year":2004,
    "item":"registered_households",
    "value":534231.0
  },
  {
    "region":"충청북도",
    "year":2005,
    "item":"registered_households",
    "value":547213.0
  },
  {
    "region":"충청북도",
    "year":2006,
    "item":"registered_households",
    "value":561762.0
  },
  {
    "region":"충청북도",
    "year":2007,
    "item":"registered_households",
    "value":574189.0
  },
  {
    "region":"충청북도",
    "year":2008,
    "item":"registered_households",
    "value":587411.0
  },
  {
    "region":"충청북도",
    "year":2009,
    "item":"registered_households",
    "value":599204.0
  },
  {
    "region":"충청북도",
    "year":2010,
    "item":"registered_households",
    "value":617431.0
  },
  {
    "region":"충청북도",
    "year":2011,
    "item":"registered_households",
    "value":627006.0
  },
  {
    "region":"충청북도",
    "year":2012,
    "item":"registered_households",
    "value":633166.0
  },
  {
    "region":"충청북도",
    "year":2013,
    "item":"registered_households",
    "value":644062.0
  },
  {
    "region":"충청북도",
    "year":2014,
    "item":"registered_households",
    "value":656321.0
  },
  {
    "region":"충청북도",
    "year":2015,
    "item":"registered_households",
    "value":669503.0
  },
  {
    "region":"충청북도",
    "year":2016,
    "item":"registered_households",
    "value":680960.0
  },
  {
    "region":"충청북도",
    "year":2017,
    "item":"registered_households",
    "value":692140.0
  },
  {
    "region":"충청북도",
    "year":2018,
    "item":"registered_households",
    "value":707220.0
  },
  {
    "region":"충청북도",
    "year":2019,
    "item":"registered_households",
    "value":722123.0
  },
  {
    "region":"충청북도",
    "year":2020,
    "item":"registered_households",
    "value":745644.0
  },
  {
    "region":"충청북도",
    "year":2021,
    "item":"registered_households",
    "value":760672.0
  },
  {
    "region":"충청북도",
    "year":2022,
    "item":"registered_households",
    "value":771848.0
  },
  {
    "region":"충청북도",
    "year":2023,
    "item":"registered_households",
    "value":779967.0
  },
  {
    "region":"충청북도",
    "year":2024,
    "item":"registered_households",
    "value":787756.0
  },
  {
    "region":"충청남도",
    "year":2000,
    "item":"registered_households",
    "value":641499.0
  },
  {
    "region":"충청남도",
    "year":2001,
    "item":"registered_households",
    "value":653610.0
  },
  {
    "region":"충청남도",
    "year":2002,
    "item":"registered_households",
    "value":666201.0
  },
  {
    "region":"충청남도",
    "year":2003,
    "item":"registered_households",
    "value":691966.0
  },
  {
    "region":"충청남도",
    "year":2004,
    "item":"registered_households",
    "value":736328.0
  },
  {
    "region":"충청남도",
    "year":2005,
    "item":"registered_households",
    "value":756073.0
  },
  {
    "region":"충청남도",
    "year":2006,
    "item":"registered_households",
    "value":774490.0
  },
  {
    "region":"충청남도",
    "year":2007,
    "item":"registered_households",
    "value":796086.0
  },
  {
    "region":"충청남도",
    "year":2008,
    "item":"registered_households",
    "value":812871.0
  },
  {
    "region":"충청남도",
    "year":2009,
    "item":"registered_households",
    "value":827846.0
  },
  {
    "region":"충청남도",
    "year":2010,
    "item":"registered_households",
    "value":854432.0
  },
  {
    "region":"충청남도",
    "year":2011,
    "item":"registered_households",
    "value":868768.0
  },
  {
    "region":"충청남도",
    "year":2012,
    "item":"registered_households",
    "value":842446.0
  },
  {
    "region":"충청남도",
    "year":2013,
    "item":"registered_households",
    "value":857699.0
  },
  {
    "region":"충청남도",
    "year":2014,
    "item":"registered_households",
    "value":871459.0
  },
  {
    "region":"충청남도",
    "year":2015,
    "item":"registered_households",
    "value":885968.0
  },
  {
    "region":"충청남도",
    "year":2016,
    "item":"registered_households",
    "value":902294.0
  },
  {
    "region":"충청남도",
    "year":2017,
    "item":"registered_households",
    "value":923499.0
  },
  {
    "region":"충청남도",
    "year":2018,
    "item":"registered_households",
    "value":943611.0
  },
  {
    "region":"충청남도",
    "year":2019,
    "item":"registered_households",
    "value":959255.0
  },
  {
    "region":"충청남도",
    "year":2020,
    "item":"registered_households",
    "value":983153.0
  },
  {
    "region":"충청남도",
    "year":2021,
    "item":"registered_households",
    "value":1001915.0
  },
  {
    "region":"충청남도",
    "year":2022,
    "item":"registered_households",
    "value":1019093.0
  },
  {
    "region":"충청남도",
    "year":2023,
    "item":"registered_households",
    "value":1035449.0
  },
  {
    "region":"충청남도",
    "year":2024,
    "item":"registered_households",
    "value":1052129.0
  },
  {
    "region":"전북특별자치도",
    "year":2000,
    "item":"registered_households",
    "value":645798.0
  },
  {
    "region":"전북특별자치도",
    "year":2001,
    "item":"registered_households",
    "value":656185.0
  },
  {
    "region":"전북특별자치도",
    "year":2002,
    "item":"registered_households",
    "value":658563.0
  },
  {
    "region":"전북특별자치도",
    "year":2003,
    "item":"registered_households",
    "value":672111.0
  },
  {
    "region":"전북특별자치도",
    "year":2004,
    "item":"registered_households",
    "value":675145.0
  },
  {
    "region":"전북특별자치도",
    "year":2005,
    "item":"registered_households",
    "value":683683.0
  },
  {
    "region":"전북특별자치도",
    "year":2006,
    "item":"registered_households",
    "value":692574.0
  },
  {
    "region":"전북특별자치도",
    "year":2007,
    "item":"registered_households",
    "value":701419.0
  },
  {
    "region":"전북특별자치도",
    "year":2008,
    "item":"registered_households",
    "value":710550.0
  },
  {
    "region":"전북특별자치도",
    "year":2009,
    "item":"registered_households",
    "value":720993.0
  },
  {
    "region":"전북특별자치도",
    "year":2010,
    "item":"registered_households",
    "value":740650.0
  },
  {
    "region":"전북특별자치도",
    "year":2011,
    "item":"registered_households",
    "value":754479.0
  },
  {
    "region":"전북특별자치도",
    "year":2012,
    "item":"registered_households",
    "value":760189.0
  },
  {
    "region":"전북특별자치도",
    "year":2013,
    "item":"registered_households",
    "value":766699.0
  },
  {
    "region":"전북특별자치도",
    "year":2014,
    "item":"registered_households",
    "value":774562.0
  },
  {
    "region":"전북특별자치도",
    "year":2015,
    "item":"registered_households",
    "value":782986.0
  },
  {
    "region":"전북특별자치도",
    "year":2016,
    "item":"registered_households",
    "value":790084.0
  },
  {
    "region":"전북특별자치도",
    "year":2017,
    "item":"registered_households",
    "value":797916.0
  },
  {
    "region":"전북특별자치도",
    "year":2018,
    "item":"registered_households",
    "value":806235.0
  },
  {
    "region":"전북특별자치도",
    "year":2019,
    "item":"registered_households",
    "value":816191.0
  },
  {
    "region":"전북특별자치도",
    "year":2020,
    "item":"registered_households",
    "value":836660.0
  },
  {
    "region":"전북특별자치도",
    "year":2021,
    "item":"registered_households",
    "value":849001.0
  },
  {
    "region":"전북특별자치도",
    "year":2022,
    "item":"registered_households",
    "value":855849.0
  },
  {
    "region":"전북특별자치도",
    "year":2023,
    "item":"registered_households",
    "value":861193.0
  },
  {
    "region":"전북특별자치도",
    "year":2024,
    "item":"registered_households",
    "value":864608.0
  },
  {
    "region":"전라남도",
    "year":2000,
    "item":"registered_households",
    "value":723932.0
  },
  {
    "region":"전라남도",
    "year":2001,
    "item":"registered_households",
    "value":728837.0
  },
  {
    "region":"전라남도",
    "year":2002,
    "item":"registered_households",
    "value":731087.0
  },
  {
    "region":"전라남도",
    "year":2003,
    "item":"registered_households",
    "value":737207.0
  },
  {
    "region":"전라남도",
    "year":2004,
    "item":"registered_households",
    "value":741768.0
  },
  {
    "region":"전라남도",
    "year":2005,
    "item":"registered_households",
    "value":751732.0
  },
  {
    "region":"전라남도",
    "year":2006,
    "item":"registered_households",
    "value":758147.0
  },
  {
    "region":"전라남도",
    "year":2007,
    "item":"registered_households",
    "value":765729.0
  },
  {
    "region":"전라남도",
    "year":2008,
    "item":"registered_households",
    "value":773087.0
  },
  {
    "region":"전라남도",
    "year":2009,
    "item":"registered_households",
    "value":783156.0
  },
  {
    "region":"전라남도",
    "year":2010,
    "item":"registered_households",
    "value":799520.0
  },
  {
    "region":"전라남도",
    "year":2011,
    "item":"registered_households",
    "value":805051.0
  },
  {
    "region":"전라남도",
    "year":2012,
    "item":"registered_households",
    "value":808682.0
  },
  {
    "region":"전라남도",
    "year":2013,
    "item":"registered_households",
    "value":815769.0
  },
  {
    "region":"전라남도",
    "year":2014,
    "item":"registered_households",
    "value":823667.0
  },
  {
    "region":"전라남도",
    "year":2015,
    "item":"registered_households",
    "value":833901.0
  },
  {
    "region":"전라남도",
    "year":2016,
    "item":"registered_households",
    "value":842688.0
  },
  {
    "region":"전라남도",
    "year":2017,
    "item":"registered_households",
    "value":851376.0
  },
  {
    "region":"전라남도",
    "year":2018,
    "item":"registered_households",
    "value":860303.0
  },
  {
    "region":"전라남도",
    "year":2019,
    "item":"registered_households",
    "value":872628.0
  },
  {
    "region":"전라남도",
    "year":2020,
    "item":"registered_households",
    "value":893152.0
  },
  {
    "region":"전라남도",
    "year":2021,
    "item":"registered_households",
    "value":903108.0
  },
  {
    "region":"전라남도",
    "year":2022,
    "item":"registered_households",
    "value":907710.0
  },
  {
    "region":"전라남도",
    "year":2023,
    "item":"registered_households",
    "value":911442.0
  },
  {
    "region":"전라남도",
    "year":2024,
    "item":"registered_households",
    "value":912412.0
  },
  {
    "region":"경상북도",
    "year":2000,
    "item":"registered_households",
    "value":943498.0
  },
  {
    "region":"경상북도",
    "year":2001,
    "item":"registered_households",
    "value":954933.0
  },
  {
    "region":"경상북도",
    "year":2002,
    "item":"registered_households",
    "value":964032.0
  },
  {
    "region":"경상북도",
    "year":2003,
    "item":"registered_households",
    "value":974099.0
  },
  {
    "region":"경상북도",
    "year":2004,
    "item":"registered_households",
    "value":985475.0
  },
  {
    "region":"경상북도",
    "year":2005,
    "item":"registered_households",
    "value":1006080.0
  },
  {
    "region":"경상북도",
    "year":2006,
    "item":"registered_households",
    "value":1030265.0
  },
  {
    "region":"경상북도",
    "year":2007,
    "item":"registered_households",
    "value":1045213.0
  },
  {
    "region":"경상북도",
    "year":2008,
    "item":"registered_households",
    "value":1058099.0
  },
  {
    "region":"경상북도",
    "year":2009,
    "item":"registered_households",
    "value":1073367.0
  },
  {
    "region":"경상북도",
    "year":2010,
    "item":"registered_households",
    "value":1101486.0
  },
  {
    "region":"경상북도",
    "year":2011,
    "item":"registered_households",
    "value":1114901.0
  },
  {
    "region":"경상북도",
    "year":2012,
    "item":"registered_households",
    "value":1125195.0
  },
  {
    "region":"경상북도",
    "year":2013,
    "item":"registered_households",
    "value":1139387.0
  },
  {
    "region":"경상북도",
    "year":2014,
    "item":"registered_households",
    "value":1153559.0
  },
  {
    "region":"경상북도",
    "year":2015,
    "item":"registered_households",
    "value":1169648.0
  },
  {
    "region":"경상북도",
    "year":2016,
    "item":"registered_households",
    "value":1180643.0
  },
  {
    "region":"경상북도",
    "year":2017,
    "item":"registered_households",
    "value":1193261.0
  },
  {
    "region":"경상북도",
    "year":2018,
    "item":"registered_households",
    "value":1207351.0
  },
  {
    "region":"경상북도",
    "year":2019,
    "item":"registered_households",
    "value":1227548.0
  },
  {
    "region":"경상북도",
    "year":2020,
    "item":"registered_households",
    "value":1254662.0
  },
  {
    "region":"경상북도",
    "year":2021,
    "item":"registered_households",
    "value":1276846.0
  },
  {
    "region":"경상북도",
    "year":2022,
    "item":"registered_households",
    "value":1286873.0
  },
  {
    "region":"경상북도",
    "year":2023,
    "item":"registered_households",
    "value":1282500.0
  },
  {
    "region":"경상북도",
    "year":2024,
    "item":"registered_households",
    "value":1291568.0
  },
  {
    "region":"경상남도",
    "year":2000,
    "item":"registered_households",
    "value":999572.0
  },
  {
    "region":"경상남도",
    "year":2001,
    "item":"registered_households",
    "value":1018039.0
  },
  {
    "region":"경상남도",
    "year":2002,
    "item":"registered_households",
    "value":1043704.0
  },
  {
    "region":"경상남도",
    "year":2003,
    "item":"registered_households",
    "value":1074004.0
  },
  {
    "region":"경상남도",
    "year":2004,
    "item":"registered_households",
    "value":1096069.0
  },
  {
    "region":"경상남도",
    "year":2005,
    "item":"registered_households",
    "value":1129320.0
  },
  {
    "region":"경상남도",
    "year":2006,
    "item":"registered_households",
    "value":1153979.0
  },
  {
    "region":"경상남도",
    "year":2007,
    "item":"registered_households",
    "value":1177923.0
  },
  {
    "region":"경상남도",
    "year":2008,
    "item":"registered_households",
    "value":1203767.0
  },
  {
    "region":"경상남도",
    "year":2009,
    "item":"registered_households",
    "value":1231461.0
  },
  {
    "region":"경상남도",
    "year":2010,
    "item":"registered_households",
    "value":1268731.0
  },
  {
    "region":"경상남도",
    "year":2011,
    "item":"registered_households",
    "value":1286678.0
  },
  {
    "region":"경상남도",
    "year":2012,
    "item":"registered_households",
    "value":1301439.0
  },
  {
    "region":"경상남도",
    "year":2013,
    "item":"registered_households",
    "value":1320887.0
  },
  {
    "region":"경상남도",
    "year":2014,
    "item":"registered_households",
    "value":1343984.0
  },
  {
    "region":"경상남도",
    "year":2015,
    "item":"registered_households",
    "value":1367142.0
  },
  {
    "region":"경상남도",
    "year":2016,
    "item":"registered_households",
    "value":1385684.0
  },
  {
    "region":"경상남도",
    "year":2017,
    "item":"registered_households",
    "value":1406011.0
  },
  {
    "region":"경상남도",
    "year":2018,
    "item":"registered_households",
    "value":1425271.0
  },
  {
    "region":"경상남도",
    "year":2019,
    "item":"registered_households",
    "value":1450822.0
  },
  {
    "region":"경상남도",
    "year":2020,
    "item":"registered_households",
    "value":1484601.0
  },
  {
    "region":"경상남도",
    "year":2021,
    "item":"registered_households",
    "value":1505971.0
  },
  {
    "region":"경상남도",
    "year":2022,
    "item":"registered_households",
    "value":1516930.0
  },
  {
    "region":"경상남도",
    "year":2023,
    "item":"registered_households",
    "value":1525502.0
  },
  {
    "region":"경상남도",
    "year":2024,
    "item":"registered_households",
    "value":1537492.0
  },
  {
    "region":"제주특별자치도",
    "year":2000,
    "item":"registered_households",
    "value":177600.0
  },
  {
    "region":"제주특별자치도",
    "year":2001,
    "item":"registered_households",
    "value":183248.0
  },
  {
    "region":"제주특별자치도",
    "year":2002,
    "item":"registered_households",
    "value":188760.0
  },
  {
    "region":"제주특별자치도",
    "year":2003,
    "item":"registered_households",
    "value":194855.0
  },
  {
    "region":"제주특별자치도",
    "year":2004,
    "item":"registered_households",
    "value":199989.0
  },
  {
    "region":"제주특별자치도",
    "year":2005,
    "item":"registered_households",
    "value":204635.0
  },
  {
    "region":"제주특별자치도",
    "year":2006,
    "item":"registered_households",
    "value":208424.0
  },
  {
    "region":"제주특별자치도",
    "year":2007,
    "item":"registered_households",
    "value":211850.0
  },
  {
    "region":"제주특별자치도",
    "year":2008,
    "item":"registered_households",
    "value":214681.0
  },
  {
    "region":"제주특별자치도",
    "year":2009,
    "item":"registered_households",
    "value":217711.0
  },
  {
    "region":"제주특별자치도",
    "year":2010,
    "item":"registered_households",
    "value":224713.0
  },
  {
    "region":"제주특별자치도",
    "year":2011,
    "item":"registered_households",
    "value":227873.0
  },
  {
    "region":"제주특별자치도",
    "year":2012,
    "item":"registered_households",
    "value":232141.0
  },
  {
    "region":"제주특별자치도",
    "year":2013,
    "item":"registered_households",
    "value":238465.0
  },
  {
    "region":"제주특별자치도",
    "year":2014,
    "item":"registered_households",
    "value":246516.0
  },
  {
    "region":"제주특별자치도",
    "year":2015,
    "item":"registered_households",
    "value":256928.0
  },
  {
    "region":"제주특별자치도",
    "year":2016,
    "item":"registered_households",
    "value":266972.0
  },
  {
    "region":"제주특별자치도",
    "year":2017,
    "item":"registered_households",
    "value":278203.0
  },
  {
    "region":"제주특별자치도",
    "year":2018,
    "item":"registered_households",
    "value":287104.0
  },
  {
    "region":"제주특별자치도",
    "year":2019,
    "item":"registered_households",
    "value":293155.0
  },
  {
    "region":"제주특별자치도",
    "year":2020,
    "item":"registered_households",
    "value":302033.0
  },
  {
    "region":"제주특별자치도",
    "year":2021,
    "item":"registered_households",
    "value":307529.0
  },
  {
    "region":"제주특별자치도",
    "year":2022,
    "item":"registered_households",
    "value":311355.0
  },
  {
    "region":"제주특별자치도",
    "year":2023,
    "item":"registered_households",
    "value":313155.0
  },
  {
    "region":"제주특별자치도",
    "year":2024,
    "item":"registered_households",
    "value":314862.0
  }
]